{
  "AbsoluteZero": {
    "NAME": "Absolute Zero",
    "DESCRIPTION": "Whenever you exhaust a card, gain !M! Chill."
  },
  "AchiCirno": {
    "NAME": "Achi Cirno",
    "DESCRIPTION": "Draw ⑨ Cards. NL Take ⑨ damage twice. NL Motivation 1：Take ⑨ damage ONCE instead."
  },
  "AssaultArmor": {
    "NAME": "Assault Armor",
    "DESCRIPTION": "Deal !D! damage to ALL enemies. NL Lose ALL Chill and Motivation, and you cannot gain Chill or Motivation again this turn."
  },
  "ButterflyFairysHelp": {
    "NAME": "Butterfly Fairy's Help",
    "DESCRIPTION": "Deal !D! damage to a random enemy for !M! times. NL Exhaust."
  },
  "Chirumiru": {
    "NAME": "Chirumiru",
    "DESCRIPTION": "Gain 2 Chill and 1 Motivation, then gain !B! Block. NL Draw !M! cards.",
    "UPGRADE_DESCRIPTION": "Gain 3 Chill and 2 Motivation, then gain !B! Block. NL Draw !M! cards."
  },
  "ColdBeer": {
    "NAME": "Cold Beer",
    "DESCRIPTION": "Gain !M! Chill and Motivation. NL Lose ⑨⑨ Strength this turn."
  },
  "ColdSprinkler": {
    "NAME": "Cold Sprinkler",
    "DESCRIPTION": "Deal !D! damage, and Upgrade a random card in hand. NL Motivation 1: Upgrade another one for each Chill you have.",
    "UPGRADE_DESCRIPTION": "Deal !D! damage, and Upgrade a random card in hand. NL Motivation 1: Upgrade ALL cards in your hand instead."
  },
  "DaiyouseisHelp": {
    "NAME": "Daiyousei's Help",
    "DESCRIPTION": "Can't be played. Retain. NL At the end of turn, gain !B! Block if this is in your hand. NL Whenever Exhausted, choose and get !M! Exhausted card(s)."
  },
  "DiamondBlizzard": {
    "NAME": "Diamond Blizzard",
    "DESCRIPTION": "Deal !D! damage and apply !M! Weakness and Vulnerable to ALL enemies."
  },
  "FairySpin": {
    "NAME": "Fairy Spin",
    "DESCRIPTION": "Deal !D! damage to a random enemy. NL Put a Dazed into your draw pile. NL Motivation X: Repeat X times."
  },
  "Flee": {
    "NAME": "Flee",
    "DESCRIPTION": "After !M! turns, escape from current combat. NL Motivation X: Escape X turns earlier, or immediately if there is at most 1 turn.",
    "UPGRADE_DESCRIPTION": "Innate. After !M! turns, escape from current combat. NL Motivation X: Escape X turns earlier, or immediately if there is at most 1 turn."
  },
  "FreezeActress": {
    "NAME": "Freeze Actress",
    "DESCRIPTION": "Get a random Attack card not in your hand. Deal damage equal to its damage. NL Motivation 1: Get 2 cards instead. Deal damage equal to the higher one.",
    "UPGRADE_DESCRIPTION": "Get a random Upgraded Attack card not in your hand. Deal damage equal to its damage. NL Motivation 1: Get 2 cards instead. Deal damage equal to the higher one."
  },
  "FreezeAtmosphere": {
    "NAME": "Freeze Atmosphere",
    "DESCRIPTION": "获得 !M! 层 寒冷 。意图为攻击的敌人获得 !M! 层 虚弱 ，其他敌人获得 !M! 层 易伤 。 消耗 。 NL 干劲 X：随机清除你身上的至多X个负面状态。"
  },
  "FreezeDrying": {
    "NAME": "冷冻干燥",
    "DESCRIPTION": "造成 !D! 点伤害。 NL 如果目标敌人已失去所有 格挡 ，再造成 !D! 点伤害。"
  },
  "FreezeTouchMe": {
    "NAME": "降温",
    "DESCRIPTION": "直到你的下个回合，每当你失去 格挡 时，获得等同于失去值一半的 格挡 （向下取整）。"
  },
  "FreezingBeams": {
    "NAME": "冷冻光线",
    "DESCRIPTION": "随机对至多 !M! 名敌人造成 !D! 点伤害。 NL 会优先攻击具有 易伤 的敌人。"
  },
  "Fridge": {
    "NAME": "冰箱",
    "DESCRIPTION": "仅在本场战斗中，当你即将死亡时，免死一次并将生命值恢复至30%。 NL 这个效果无法叠加。",
    "UPGRADE_DESCRIPTION": "固有 。 NL 仅在本场战斗中，当你即将死亡时，免死一次并将生命值恢复至30%。 NL 这个效果无法叠加。"
  },
  "FrostKing": {
    "NAME": "霜冻之王",
    "DESCRIPTION": "每当你在战斗中临时获得一张牌，就获得 !M! 点 干劲 和 !B! 点 格挡 。"
  },
  "FrostMeteor": {
    "NAME": "凝结流星",
    "DESCRIPTION": "造成 !D! 点伤害。 NL 下 !M! 次 消耗 攻击牌或技能牌时，改为将其置入弃牌堆。"
  },
  "FrostPillars": {
    "NAME": "冰柱",
    "DESCRIPTION": "获得 !B! 点格挡。 NL 下一名攻击你的敌人将会受到 !M! 点伤害。"
  },
  "FrozenFreeze": {
    "NAME": "急速冷冻法",
    "DESCRIPTION": "失去所有 格挡 ，然后获得 !B! 点 格挡 。"
  },
  "FrozenSpring": {
    "NAME": "冰冻温泉",
    "DESCRIPTION": "下⑨次 消耗 一张牌时，恢复 !M! 点生命。",
    "UPGRADE_DESCRIPTION": "下⑨次 消耗 一张牌时，恢复 !M! 点生命并获得 !M! 点 干劲 。"
  },
  "GiganticIceMagic": {
    "NAME": "超大型冰冻魔法",
    "DESCRIPTION": "造成 !D! 点伤害。你在本回合内每打出过一张其他牌，伤害就减少12点。"
  },
  "GreatCrusher": {
    "NAME": "巨冰破碎",
    "DESCRIPTION": "随机对敌人造成 !D! 点伤害 !M! 次。 NL 从第二次开始基础伤害比上一次提高 1 点。"
  },
  "Hailstorm": {
    "NAME": "冰雹暴风",
    "DESCRIPTION": "对所有敌人造成等同于你已 消耗 的牌数量 !M! 倍的伤害。",
    "EXTENDED_DESCRIPTION": [
      "（造成 !D! 点伤害。）"
    ]
  },
  "HighSpirit": {
    "NAME": "斗志昂扬",
    "DESCRIPTION": "如果你拥有 寒冷 ，抽 !M! 张牌；否则获得 1 层 寒冷 。 NL 以同样的方法判定 干劲 。"
  },
  "IceArmor": {
    "NAME": "寒冰铠甲",
    "DESCRIPTION": "获得 !B! 点格挡两次。如果你的手牌数至少为 !M! ，则获得 1 层 寒冷 。"
  },
  "IceBarrier": {
    "NAME": "冰冻屏障",
    "DESCRIPTION": "获得 !B! 点 格挡 。"
  },
  "IceFall": {
    "NAME": "冰瀑",
    "DESCRIPTION": "当前每有一名敌人，获得 !M! 点 干劲 。 NL 对所有敌人造成 !D! 点伤害。"
  },
  "IceFishing": {
    "NAME": "冰钓术",
    "DESCRIPTION": "将随机牌置入你的手牌，直至手牌数量达到上限。 NL 消耗 。",
    "UPGRADE_DESCRIPTION": "将随机牌置入你的手牌，直至手牌数量达到上限。"
  },
  "IceGrain": {
    "NAME": "冰粒",
    "DESCRIPTION": "造成 !D! 点伤害。"
  },
  "IceKick": {
    "NAME": "旋转踢",
    "DESCRIPTION": "受到 !M! 点伤害，然后造成 !D! 点伤害。"
  },
  "IceMachineGun": {
    "NAME": "冰柱机枪",
    "DESCRIPTION": "随机对敌人造成 !D! 点伤害 !M! 次。"
  },
  "IceSpear": {
    "NAME": "冰枪术",
    "DESCRIPTION": "造成 !D! 点伤害。 NL 如果目标敌人具有负面状态，则改为造成 !M! 点伤害。"
  },
  "IcicleConeCrush": {
    "NAME": "天冰乱坠",
    "DESCRIPTION": "抽 !M! 张牌，检查每张牌的 类别 。 NL 攻击牌：造成 !D! 点伤害； NL 技能牌：获得 !B! 点格挡； NL 否则获得2层 寒冷 与1点 干劲 。"
  },
  "IcicleShot": {
    "NAME": "冰锥射击",
    "DESCRIPTION": "造成 !D! 点伤害两次。 NL 干劲 1：改为造成 !D! 点伤害三次。"
  },
  "ImFunky": {
    "NAME": "迷之舞步",
    "DESCRIPTION": "每抽一张牌，获得 !M! 层 寒冷 。 NL 虚无 。",
    "UPGRADE_DESCRIPTION": "每抽一张牌，获得 !M! 层 寒冷 。"
  },
  "LunaticFairysHelp": {
    "NAME": "狂气妖精之援",
    "DESCRIPTION": "每回合开始时多获得 [E] 。每当你抽到一张牌，都将其 消耗 。 NL 每当你 消耗 一张攻击牌、技能牌或能力牌时，获得对应种类的一张随机牌。",
    "UPGRADE_DESCRIPTION": "固有 。每回合开始时多获得 [E] 。每当你抽到一张牌，都将其 消耗 。 NL 每当你 消耗 一张攻击牌、技能牌或能力牌时，获得对应种类的一张随机牌。"
  },
  "MinusK": {
    "NAME": "负K",
    "DESCRIPTION": "下X次，当你 消耗 一张牌时，获得 [E] 。 消耗 。",
    "UPGRADE_DESCRIPTION": "下X+1次，当你 消耗 一张牌时，获得 [E] 。 消耗 。"
  },
  "NineMathTextbooks": {
    "NAME": "⑨章算术",
    "DESCRIPTION": "选择一种 类别 。 NL 抽 !M! 张牌，丢弃不属于所选 类别 的牌。"
  },
  "PerfectFreeze": {
    "NAME": "完美冻结",
    "DESCRIPTION": "干劲 3：对所有敌人造成若干次 !D! 点伤害，次数等同于你拥有的 寒冷 层数。",
    "UPGRADE_DESCRIPTION": "干劲 2：对所有敌人造成若干次 !D! 点伤害，次数等同于你拥有的 寒冷 层数+1。",
    "EXTENDED_DESCRIPTION": [
      "（造成", "次伤害。）"
    ]
  },
  "PerfectGlacialist": {
    "NAME": "完美冰川学家",
    "DESCRIPTION": "造成 !D! 点伤害。 NL 获得数额等同于被格挡伤害的 格挡 。"
  },
  "PerfectSummerIce": {
    "NAME": "完美的夏日之冰",
    "DESCRIPTION": "每回合开始时，随机将 !M! 张类别与稀有度互不相同的牌加入你的手牌。"
  },
  "SecretSmoothie": {
    "NAME": "秘制冰沙",
    "DESCRIPTION": "在本回合结束时，恢复等同于 寒冷 层数的生命。 NL 消耗 。",
    "UPGRADE_DESCRIPTION": "保留 。 NL 在本回合结束时，恢复等同于 寒冷 层数的生命。 NL 消耗 。"
  },
  "ShowOff": {
    "NAME": "夸耀",
    "DESCRIPTION": "获得 !M! 层 寒冷 与 !M! 点 干劲。"
  },
  "SnowmanInMidsummer": {
    "NAME": "盛夏的雪人",
    "DESCRIPTION": "消耗 手牌中的所有非攻击牌。 NL 获得等量的随机攻击牌，并且这些牌在本场战斗中的耗能减少1点。 NL 消耗 。",
    "UPGRADE_DESCRIPTION": "消耗 手牌中的所有非攻击牌。 NL 获得等量 升级 过的随机攻击牌，并且这些牌在本场战斗中的耗能减少1点。 NL 消耗 。"
  },
  "Sunbathe": {
    "NAME": "日光浴",
    "DESCRIPTION": "获得 !D! 点 格挡 与4点 干劲。 NL 抽 !M! 张牌。 NL 将两张 灼伤 加入你的手牌。",
    "UPGRADE_DESCRIPTION": "获得 !D! 点 格挡 与5点 干劲。 NL 抽 !M! 张牌。 NL 将三张 灼伤 加入你的手牌。"
  },
  "SwordFreezer": {
    "NAME": "剑式制冰器",
    "DESCRIPTION": "你手中每有一张攻击牌，就获得 !M! 点 活力 。 NL 干劲 1：每有一张技能牌，就获得 !B! 点 格挡 。"
  },
  "TengusCamera": {
    "NAME": "天狗的相机",
    "DESCRIPTION": "将手牌复制并洗入抽牌堆中。 NL 消耗 。"
  },
  "ThreeFairiesHelp": {
    "NAME": "三妖精之援",
    "DESCRIPTION": "随机选择一种 类别 。获得所选 类别 的一张随机牌，其在本回合的费用为 0。 消耗 。 NL 干劲 1：改为发现一张所选 类别 的牌。",
    "UPGRADE_DESCRIPTION": "选择一种 类别 。获得所选 类别 的一张随机牌，其在本回合的费用为 0。 消耗 。 NL 干劲 1：改为发现一张所选 类别 的牌。"
  },
  "WishOfBreeze": {
    "NAME": "微风祈愿",
    "DESCRIPTION": "每回合结束时，随机将弃牌堆中的 !M! 张牌返回手牌。"
  },
  
  "IceCharge": {
    "NAME": "冰冻冲刺",
    "DESCRIPTION": "造成 !D! 点伤害。每造成 !M! 点未被格挡的伤害，就获得 1 层 寒冷 。"
  },
  "SandbagFairy": {
    "NAME": "沙包妖精",
    "DESCRIPTION": "直到你的下个回合，每当你完全格挡一次伤害，就获得 !M! 点 干劲 。"
  },
  "IceTornado": {
    "NAME": "碎冰龙卷",
    "DESCRIPTION": "消耗 手牌中所有攻击牌。 NL 每 消耗 一张，造成 !D! 张伤害。"
  },
  "IceExperience": {
    "NAME": "寒冰体验",
    "DESCRIPTION": "将你的手牌替换为等量的随机牌。 NL 回合结束时，将手牌 消耗 ，随机取回等量的原有手牌，多余的置入弃牌堆。 消耗 。",
    "UPGRADE_DESCRIPTION": "将你的手牌替换为等量的 升级 过的随机牌。 NL 回合结束时，将手牌 消耗 ，选择等量的原有手牌取回，多余的置入弃牌堆。 消耗 。"
  },
  
  "Occultation": {
    "NAME": "掩星",
    "DESCRIPTION": "将抽牌堆的卡全部放入弃牌堆，每一张使你获得1点 格挡 。",
    "UPGRADE_DESCRIPTION": "将抽牌堆的卡全部放入弃牌堆，每一张使你获得1点 格挡 。 NL 获得3点 格挡 。",
    "EXTENDED_DESCRIPTION": [
      "（获得 !B! 点格挡）",
      ""
    ]
  }
}